myabcm_corporate_admin_api/__init__.py
myabcm_corporate_admin_api/corporate_admin_module.py
myabcm_corporate_admin_api-0.1.3.dist-info/licenses/LICENSE
myabcm_corporate_admin_api-0.1.3.dist-info/METADATA
myabcm_corporate_admin_api-0.1.3.dist-info/WHEEL
myabcm_corporate_admin_api-0.1.3.dist-info/top_level.txt
myabcm_corporate_admin_api-0.1.3.dist-info/RECORD
